unrest_schema/__init__.py
unrest_schema/http.py
unrest_schema/pagination.py
unrest_schema/urls.py
unrest_schema/utils.py
unrest_schema/views.py
django_unrest_schema-0.0.4.dist-info/LICENSE
django_unrest_schema-0.0.4.dist-info/METADATA
django_unrest_schema-0.0.4.dist-info/WHEEL
django_unrest_schema-0.0.4.dist-info/top_level.txt
django_unrest_schema-0.0.4.dist-info/RECORD
