Metadata-Version: 2.1
Name: django-unrest-schema
Version: 0.0.4
Summary: A library for serving django forms using json schema and a restful api.
Home-page: https://github.com/chriscauley/django-unrest-schema
Author: Chris Cauley
Author-email: chris@lablackey.com
License: MIT
Keywords: utils,django,jsonschema
License-File: LICENSE
Requires-Dist: django >=4.0.0
